LICENSE
LICENSE-APACHE
LICENSE-GPL
MANIFEST.in
README.md
pyproject.toml
setup.py
src/viur/datastore/__init__.py
src/viur/datastore/cache.py
src/viur/datastore/config.py
src/viur/datastore/errors.py
src/viur/datastore/query.py
src/viur/datastore/simdjson.cpp
src/viur/datastore/simdjson.h
src/viur/datastore/transport.cpp
src/viur/datastore/transport.pyx
src/viur/datastore/types.py
src/viur/datastore/utils.py
src/viur_datastore.egg-info/PKG-INFO
src/viur_datastore.egg-info/SOURCES.txt
src/viur_datastore.egg-info/dependency_links.txt
src/viur_datastore.egg-info/requires.txt
src/viur_datastore.egg-info/top_level.txt