Metadata-Version: 2.1
Name: viur-datastore
Version: 1.3.14
Summary: A faster replacement for google-cloud-datastore
Home-page: https://github.com/viur-framework/viur-datastore
Author: Tobias Steinrücken, Stefan Kögl
Author-email: devs@viur.dev
Maintainer: Stefan Kögl
Maintainer-email: devs@viur.dev
Classifier: Programming Language :: Python :: 3
Classifier: Development Status :: 5 - Production/Stable
Classifier: Intended Audience :: Developers
Classifier: Topic :: Database :: Front-Ends
Requires-Python: >=3.10
License-File: LICENSE
License-File: LICENSE-APACHE
License-File: LICENSE-GPL
Requires-Dist: google-cloud-datastore>=2.0
Requires-Dist: google-auth>=2.0
Requires-Dist: requests>=2.0
